clickd/__init__.py
clickd-0.1.1.dist-info/LICENSE
clickd-0.1.1.dist-info/METADATA
clickd-0.1.1.dist-info/WHEEL
clickd-0.1.1.dist-info/RECORD
