Metadata-Version: 2.1
Name: clickd
Version: 0.1.1
Summary: Click group wrapper for loading click commands from separate files.
Author: Tyler Curtis Jowers
Author-email: jowerstc@outlook.com
Requires-Python: >=3.12,<4.0
Classifier: Programming Language :: Python :: 3
Classifier: Programming Language :: Python :: 3.12
Requires-Dist: click (>=8.1.7,<9.0.0)
